CHANGES.txt
LICENSE.txt
MANIFEST.in
README.rst
setup.py
Znet.egg-info/PKG-INFO
Znet.egg-info/SOURCES.txt
Znet.egg-info/dependency_links.txt
Znet.egg-info/requires.txt
Znet.egg-info/top_level.txt
mlexpress/mlx.py