Metadata-Version: 2.1
Name: Znet
Version: 0.0.1
Summary: Devision tree
Home-page: https://github.com/zeroknowledgediscovery/
Author: zed.uchicago.edu
Author-email: ishanu@uchicago.edu
License: LICENSE.txt
Download-URL: https://github.com/zeroknowledgediscovery/Cynet/archive/0.0.1.tar.gz
Keywords: decision,trees
Platform: UNKNOWN
Classifier: Development Status :: 4 - Beta
Classifier: Intended Audience :: Developers
Classifier: Intended Audience :: Science/Research
Classifier: Topic :: Scientific/Engineering :: Information Analysis
Classifier: Topic :: Software Development :: Libraries
Classifier: License :: OSI Approved :: MIT License
Classifier: Programming Language :: Python :: 2.7
Requires-Python: ==2.7.*
